points2regions/__init__.py
points2regions/_points2regions.py
points2regions/benchmark.py
points2regions/geojson.py
points2regions/utils.py
points2regions-0.0.6.dist-info/LICENSE
points2regions-0.0.6.dist-info/METADATA
points2regions-0.0.6.dist-info/WHEEL
points2regions-0.0.6.dist-info/top_level.txt
points2regions-0.0.6.dist-info/RECORD
